[
  {
    "anonymous": false,
    "inputs": [
      {
        "indexed": false,
        "internalType": "uint256",
        "name": "base_chainId",
        "type": "uint256"
      },
      {
        "indexed": false,
        "internalType": "uint160",
        "name": "base_token",
        "type": "uint160"
      },
      {
        "indexed": false,
        "internalType": "string",
        "name": "name",
        "type": "string"
      },
      {
        "indexed": false,
        "internalType": "string",
        "name": "symbol",
        "type": "string"
      },
      {
        "indexed": false,
        "internalType": "uint8",
        "name": "decimals",
        "type": "uint8"
      },
      {
        "indexed": false,
        "internalType": "uint128",
        "name": "amount",
        "type": "uint128"
      },
      {
        "indexed": false,
        "internalType": "int8",
        "name": "recipient_wid",
        "type": "int8"
      },
      {
        "indexed": false,
        "internalType": "uint256",
        "name": "recipient_addr",
        "type": "uint256"
      },
      {
        "indexed": false,
        "internalType": "uint256",
        "name": "value",
        "type": "uint256"
      },
      {
        "indexed": false,
        "internalType": "uint256",
        "name": "expected_evers",
        "type": "uint256"
      },
      {
        "indexed": false,
        "internalType": "bytes",
        "name": "payload",
        "type": "bytes"
      }
    ],
    "name": "AlienTransfer",
    "type": "event"
  },
  {
    "anonymous": false,
    "inputs": [
      {
        "indexed": false,
        "internalType": "enum IMultiVaultFacetTokens.TokenType",
        "name": "_type",
        "type": "uint8"
      },
      {
        "indexed": false,
        "internalType": "address",
        "name": "sender",
        "type": "address"
      },
      {
        "indexed": false,
        "internalType": "address",
        "name": "token",
        "type": "address"
      },
      {
        "indexed": false,
        "internalType": "int8",
        "name": "recipient_wid",
        "type": "int8"
      },
      {
        "indexed": false,
        "internalType": "uint256",
        "name": "recipient_addr",
        "type": "uint256"
      },
      {
        "indexed": false,
        "internalType": "uint256",
        "name": "amount",
        "type": "uint256"
      },
      {
        "indexed": false,
        "internalType": "uint256",
        "name": "fee",
        "type": "uint256"
      }
    ],
    "name": "Deposit",
    "type": "event"
  },
  {
    "anonymous": false,
    "inputs": [
      {
        "indexed": false,
        "internalType": "int8",
        "name": "native_wid",
        "type": "int8"
      },
      {
        "indexed": false,
        "internalType": "uint256",
        "name": "native_addr",
        "type": "uint256"
      },
      {
        "indexed": false,
        "internalType": "uint128",
        "name": "amount",
        "type": "uint128"
      },
      {
        "indexed": false,
        "internalType": "int8",
        "name": "recipient_wid",
        "type": "int8"
      },
      {
        "indexed": false,
        "internalType": "uint256",
        "name": "recipient_addr",
        "type": "uint256"
      },
      {
        "indexed": false,
        "internalType": "uint256",
        "name": "value",
        "type": "uint256"
      },
      {
        "indexed": false,
        "internalType": "uint256",
        "name": "expected_evers",
        "type": "uint256"
      },
      {
        "indexed": false,
        "internalType": "bytes",
        "name": "payload",
        "type": "bytes"
      }
    ],
    "name": "NativeTransfer",
    "type": "event"
  },
  {
    "anonymous": false,
    "inputs": [
      {
        "indexed": false,
        "internalType": "address",
        "name": "recipient",
        "type": "address"
      },
      {
        "indexed": false,
        "internalType": "uint256",
        "name": "id",
        "type": "uint256"
      },
      {
        "indexed": false,
        "internalType": "uint256",
        "name": "amount",
        "type": "uint256"
      }
    ],
    "name": "PendingWithdrawalCancel",
    "type": "event"
  },
  {
    "anonymous": false,
    "inputs": [
      {
        "indexed": false,
        "internalType": "address",
        "name": "recipient",
        "type": "address"
      },
      {
        "indexed": false,
        "internalType": "uint256",
        "name": "id",
        "type": "uint256"
      },
      {
        "indexed": false,
        "internalType": "address",
        "name": "token",
        "type": "address"
      },
      {
        "indexed": false,
        "internalType": "uint256",
        "name": "amount",
        "type": "uint256"
      },
      {
        "indexed": false,
        "internalType": "bytes32",
        "name": "payloadId",
        "type": "bytes32"
      }
    ],
    "name": "PendingWithdrawalCreated",
    "type": "event"
  },
  {
    "anonymous": false,
    "inputs": [
      {
        "indexed": false,
        "internalType": "address",
        "name": "recipient",
        "type": "address"
      },
      {
        "indexed": false,
        "internalType": "uint256",
        "name": "id",
        "type": "uint256"
      }
    ],
    "name": "PendingWithdrawalFill",
    "type": "event"
  },
  {
    "anonymous": false,
    "inputs": [
      {
        "indexed": false,
        "internalType": "address",
        "name": "recipient",
        "type": "address"
      },
      {
        "indexed": false,
        "internalType": "uint256",
        "name": "id",
        "type": "uint256"
      }
    ],
    "name": "PendingWithdrawalForce",
    "type": "event"
  },
  {
    "anonymous": false,
    "inputs": [
      {
        "indexed": false,
        "internalType": "address",
        "name": "recipient",
        "type": "address"
      },
      {
        "indexed": false,
        "internalType": "uint256",
        "name": "id",
        "type": "uint256"
      },
      {
        "indexed": false,
        "internalType": "enum IMultiVaultFacetPendingWithdrawals.ApproveStatus",
        "name": "approveStatus",
        "type": "uint8"
      }
    ],
    "name": "PendingWithdrawalUpdateApproveStatus",
    "type": "event"
  },
  {
    "anonymous": false,
    "inputs": [
      {
        "indexed": false,
        "internalType": "address",
        "name": "recipient",
        "type": "address"
      },
      {
        "indexed": false,
        "internalType": "uint256",
        "name": "id",
        "type": "uint256"
      },
      {
        "indexed": false,
        "internalType": "uint256",
        "name": "bounty",
        "type": "uint256"
      }
    ],
    "name": "PendingWithdrawalUpdateBounty",
    "type": "event"
  },
  {
    "anonymous": false,
    "inputs": [
      {
        "indexed": false,
        "internalType": "address",
        "name": "recipient",
        "type": "address"
      },
      {
        "indexed": false,
        "internalType": "uint256",
        "name": "id",
        "type": "uint256"
      },
      {
        "indexed": false,
        "internalType": "uint256",
        "name": "amount",
        "type": "uint256"
      }
    ],
    "name": "PendingWithdrawalWithdraw",
    "type": "event"
  },
  {
    "inputs": [
      {
        "internalType": "uint256",
        "name": "id",
        "type": "uint256"
      },
      {
        "internalType": "uint256",
        "name": "amount",
        "type": "uint256"
      },
      {
        "components": [
          {
            "internalType": "int8",
            "name": "wid",
            "type": "int8"
          },
          {
            "internalType": "uint256",
            "name": "addr",
            "type": "uint256"
          }
        ],
        "internalType": "struct IEverscale.EverscaleAddress",
        "name": "recipient",
        "type": "tuple"
      },
      {
        "internalType": "uint256",
        "name": "expected_evers",
        "type": "uint256"
      },
      {
        "internalType": "bytes",
        "name": "payload",
        "type": "bytes"
      },
      {
        "internalType": "uint256",
        "name": "bounty",
        "type": "uint256"
      }
    ],
    "name": "cancelPendingWithdrawal",
    "outputs": [],
    "stateMutability": "payable",
    "type": "function"
  },
  {
    "inputs": [
      {
        "components": [
          {
            "internalType": "address",
            "name": "recipient",
            "type": "address"
          },
          {
            "internalType": "uint256",
            "name": "id",
            "type": "uint256"
          }
        ],
        "internalType": "struct IMultiVaultFacetPendingWithdrawals.PendingWithdrawalId[]",
        "name": "pendingWithdrawalIds",
        "type": "tuple[]"
      }
    ],
    "name": "forceWithdraw",
    "outputs": [],
    "stateMutability": "nonpayable",
    "type": "function"
  },
  {
    "inputs": [
      {
        "internalType": "address",
        "name": "user",
        "type": "address"
      },
      {
        "internalType": "uint256",
        "name": "id",
        "type": "uint256"
      }
    ],
    "name": "pendingWithdrawals",
    "outputs": [
      {
        "components": [
          {
            "internalType": "address",
            "name": "token",
            "type": "address"
          },
          {
            "internalType": "uint256",
            "name": "amount",
            "type": "uint256"
          },
          {
            "internalType": "uint256",
            "name": "bounty",
            "type": "uint256"
          },
          {
            "internalType": "uint256",
            "name": "timestamp",
            "type": "uint256"
          },
          {
            "internalType": "enum IMultiVaultFacetPendingWithdrawals.ApproveStatus",
            "name": "approveStatus",
            "type": "uint8"
          },
          {
            "internalType": "uint256",
            "name": "chainId",
            "type": "uint256"
          },
          {
            "components": [
              {
                "internalType": "address",
                "name": "recipient",
                "type": "address"
              },
              {
                "internalType": "bytes",
                "name": "payload",
                "type": "bytes"
              },
              {
                "internalType": "bool",
                "name": "strict",
                "type": "bool"
              }
            ],
            "internalType": "struct IMultiVaultFacetWithdraw.Callback",
            "name": "callback",
            "type": "tuple"
          }
        ],
        "internalType": "struct IMultiVaultFacetPendingWithdrawals.PendingWithdrawalParams",
        "name": "",
        "type": "tuple"
      }
    ],
    "stateMutability": "view",
    "type": "function"
  },
  {
    "inputs": [
      {
        "internalType": "address",
        "name": "user",
        "type": "address"
      }
    ],
    "name": "pendingWithdrawalsPerUser",
    "outputs": [
      {
        "internalType": "uint256",
        "name": "",
        "type": "uint256"
      }
    ],
    "stateMutability": "view",
    "type": "function"
  },
  {
    "inputs": [
      {
        "internalType": "address",
        "name": "_token",
        "type": "address"
      }
    ],
    "name": "pendingWithdrawalsTotal",
    "outputs": [
      {
        "internalType": "uint256",
        "name": "",
        "type": "uint256"
      }
    ],
    "stateMutability": "view",
    "type": "function"
  },
  {
    "inputs": [
      {
        "components": [
          {
            "internalType": "address",
            "name": "recipient",
            "type": "address"
          },
          {
            "internalType": "uint256",
            "name": "id",
            "type": "uint256"
          }
        ],
        "internalType": "struct IMultiVaultFacetPendingWithdrawals.PendingWithdrawalId[]",
        "name": "pendingWithdrawalId",
        "type": "tuple[]"
      },
      {
        "internalType": "enum IMultiVaultFacetPendingWithdrawals.ApproveStatus[]",
        "name": "approveStatus",
        "type": "uint8[]"
      }
    ],
    "name": "setPendingWithdrawalApprove",
    "outputs": [],
    "stateMutability": "nonpayable",
    "type": "function"
  },
  {
    "inputs": [
      {
        "components": [
          {
            "internalType": "address",
            "name": "recipient",
            "type": "address"
          },
          {
            "internalType": "uint256",
            "name": "id",
            "type": "uint256"
          }
        ],
        "internalType": "struct IMultiVaultFacetPendingWithdrawals.PendingWithdrawalId",
        "name": "pendingWithdrawalId",
        "type": "tuple"
      },
      {
        "internalType": "enum IMultiVaultFacetPendingWithdrawals.ApproveStatus",
        "name": "approveStatus",
        "type": "uint8"
      }
    ],
    "name": "setPendingWithdrawalApprove",
    "outputs": [],
    "stateMutability": "nonpayable",
    "type": "function"
  },
  {
    "inputs": [
      {
        "internalType": "uint256",
        "name": "id",
        "type": "uint256"
      },
      {
        "internalType": "uint256",
        "name": "bounty",
        "type": "uint256"
      }
    ],
    "name": "setPendingWithdrawalBounty",
    "outputs": [],
    "stateMutability": "nonpayable",
    "type": "function"
  },
  {
    "inputs": [
      {
        "internalType": "address",
        "name": "token",
        "type": "address"
      }
    ],
    "name": "withdrawalLimits",
    "outputs": [
      {
        "components": [
          {
            "internalType": "uint256",
            "name": "undeclared",
            "type": "uint256"
          },
          {
            "internalType": "uint256",
            "name": "daily",
            "type": "uint256"
          },
          {
            "internalType": "bool",
            "name": "enabled",
            "type": "bool"
          }
        ],
        "internalType": "struct IMultiVaultFacetPendingWithdrawals.WithdrawalLimits",
        "name": "",
        "type": "tuple"
      }
    ],
    "stateMutability": "view",
    "type": "function"
  },
  {
    "inputs": [
      {
        "internalType": "address",
        "name": "token",
        "type": "address"
      },
      {
        "internalType": "uint256",
        "name": "withdrawalPeriodId",
        "type": "uint256"
      }
    ],
    "name": "withdrawalPeriods",
    "outputs": [
      {
        "components": [
          {
            "internalType": "uint256",
            "name": "total",
            "type": "uint256"
          },
          {
            "internalType": "uint256",
            "name": "considered",
            "type": "uint256"
          }
        ],
        "internalType": "struct IMultiVaultFacetPendingWithdrawals.WithdrawalPeriodParams",
        "name": "",
        "type": "tuple"
      }
    ],
    "stateMutability": "view",
    "type": "function"
  }
]
